pregistry/__init__.py
pregistry/_version.py
pregistry/classproperty.py
pregistry/loader.py
pregistry/plugin.py
pregistry/registry.py
PluginRegistry-0.3.2.dist-info/LICENSE.txt
PluginRegistry-0.3.2.dist-info/METADATA
PluginRegistry-0.3.2.dist-info/WHEEL
PluginRegistry-0.3.2.dist-info/top_level.txt
PluginRegistry-0.3.2.dist-info/zip-safe
PluginRegistry-0.3.2.dist-info/RECORD
